[{"name": "鑫裕建设", "lon": 117.22, "lat": 39.12, "datestr": "1980年12月12日"}, {"name": "江苏华能建设工程集团有限公司", "lon": 119.48, "lat": 31.42, "datestr": "1982年09月30日"}, {"name": "泰达建设", "lon": 117.22, "lat": 39.12, "datestr": "1984年11月15日"}, {"name": "中航地产股份有限公司", "lon": 114.05, "lat": 22.53, "datestr": "1985年05月29日"}, {"name": "南洋电缆集团", "lon": 121.43, "lat": 31.18, "datestr": "1985年08月30日"}, {"name": "华鼎建筑装饰工程有限公司", "lon": 120.47, "lat": 36.1, "datestr": "1985年10月18日"}, {"name": "深圳市路桥建设集团有限公司", "lon": 114.12, "lat": 22.55, "datestr": "1986年12月31日"}, {"name": "深圳市天华建筑设计有限公司", "lon": 114.05, "lat": 22.53, "datestr": "1987年11月14日"}, {"name": "湖南格瑞工程建设有限公司", "lon": 113.03, "lat": 28.18, "datestr": "1988年10月15日"}, {"name": "江苏启安建设集团有限公司", "lon": 121.65, "lat": 31.82, "datestr": "1989年02月23日"}, {"name": "西安建工第四建筑有限责任公司", "lon": 108.93, "lat": 34.27, "datestr": "1990年08月03日"}, {"name": "南京建工集团有限公司", "lon": 118.77, "lat": 32.0, "datestr": "1990年10月05日"}, {"name": "广州华森建筑与工程设计顾问有限公司", "lon": 113.27, "lat": 23.13, "datestr": "1991年7月15日"}, {"name": "重庆南方集团有限公司", "lon": 106.5, "lat": 29.5, "datestr": "1992年02月18日"}, {"name": "际高建业有限公司", "lon": 116.43, "lat": 39.92, "datestr": "1992年05月12日"}, {"name": "重庆中渝物业发展有限公司", "lon": 106.63, "lat": 29.72, "datestr": "1992年06月11日"}, {"name": "世茂股份", "lon": 121.48, "lat": 31.23, "datestr": "1992年07月01日"}, {"name": "津东房地产", "lon": 117.18, "lat": 39.15, "datestr": "1992年08月21日"}, {"name": "中土集团南方建设有限公司", "lon": 113.55, "lat": 22.27, "datestr": "1992年09月21日"}, {"name": "万达", "lon": 114.3, "lat": 30.57, "datestr": "1992年09月28日"}, {"name": "杭州诺贝尔集团", "lon": 120.3, "lat": 30.42, "datestr": "1992年12月15日"}, {"name": "深圳市园林集团", "lon": 114.12, "lat": 22.55, "datestr": "1993年02月09日"}, {"name": "新业", "lon": 113.3, "lat": 22.8, "datestr": "1993年02月13日"}, {"name": "仁恒房地产", "lon": 121.53, "lat": 31.22, "datestr": "1993年03月22日"}, {"name": "隆生企业", "lon": 114.4, "lat": 23.08, "datestr": "1993年03月26日"}, {"name": "锦都建设", "lon": 121.43, "lat": 31.18, "datestr": "1993年03月28日"}, {"name": "融汇房地产", "lon": 117.57, "lat": 34.87, "datestr": "1993年04月22日"}, {"name": "华夏幸福基业", "lon": 116.43, "lat": 39.92, "datestr": "1993年05月28日"}, {"name": "同济科技实业", "lon": 121.52, "lat": 31.27, "datestr": "1993年06月11日"}, {"name": "中交第四航务工程勘察设计院有限公司", "lon": 113.25, "lat": 23.1, "datestr": "1993年08月25日"}, {"name": "深圳泛华工程集团有限公司", "lon": 114.05, "lat": 22.53, "datestr": "1993年08月26日"}, {"name": "北京帕克国际工程咨询股份有限公司", "lon": 116.43, "lat": 39.92, "datestr": "1993年09月10日"}, {"name": "上海陆道工程设计管理股份有限公司", "lon": 121.4, "lat": 31.25, "datestr": "1993年9月20日"}, {"name": "中粮地产(北京)", "lon": 116.42, "lat": 39.93, "datestr": "1993年10月08日"}, {"name": "深圳市佳华房地产开发有限公司", "lon": 113.9, "lat": 22.57, "datestr": "1993年10月20日"}, {"name": "深圳城建", "lon": 114.12, "lat": 22.55, "datestr": "1993年12月02日"}, {"name": "三湘股份有限公司", "lon": 121.52, "lat": 31.27, "datestr": "1994年01月20日"}, {"name": "海天实业", "lon": 114.3, "lat": 30.6, "datestr": "1994年01月26日"}, {"name": "北京金科地产", "lon": 116.43, "lat": 39.92, "datestr": "1994年03月29日"}, {"name": "丽贝亚", "lon": 116.22, "lat": 39.9, "datestr": "1994年06月18日"}, {"name": "万科房地产", "lon": 118.08, "lat": 24.52, "datestr": "1994年06月30日"}, {"name": "林同棪国际", "lon": 106.63, "lat": 29.72, "datestr": "1994年07月20日"}, {"name": "南京富力地产", "lon": 118.85, "lat": 31.95, "datestr": "1994年08月31日"}, {"name": "广州祥能投资集团有限公司", "lon": 113.25, "lat": 23.1, "datestr": "1994年11月18日"}, {"name": "中弘控股", "lon": 116.43, "lat": 39.92, "datestr": "1995年01月28日"}, {"name": "武汉一安", "lon": 114.3, "lat": 30.57, "datestr": "1995年02月17日"}, {"name": "四川兴源环亚房地产开发有限公司", "lon": 105.57, "lat": 30.52, "datestr": "1995年03月20日"}, {"name": "天同宏基集团股份有限公司", "lon": 116.28, "lat": 39.85, "datestr": "1995年04月05日"}, {"name": "中南恒展", "lon": 113.15, "lat": 23.03, "datestr": "1995年05月04日"}, {"name": "青岛海信房地产股份有限公司分支机构", "lon": 120.38, "lat": 36.07, "datestr": "1995年07月19日"}, {"name": "海岸投资", "lon": 113.92, "lat": 22.52, "datestr": "1995年08月02日"}, {"name": "欧琳厨具", "lon": 121.53, "lat": 29.83, "datestr": "1995年08月23日"}, {"name": "信地置业", "lon": 117.3, "lat": 31.87, "datestr": "1995年08月25日"}, {"name": "深圳市国策房地产土地估价有限公司", "lon": 114.05, "lat": 22.53, "datestr": "1995年09月29日"}, {"name": "众森实业", "lon": 116.37, "lat": 39.92, "datestr": "1995年10月13日"}, {"name": "北京爱地鑫装饰艺术有限责任公司", "lon": 116.3, "lat": 39.95, "datestr": "1995年11月28日"}, {"name": "广东珠光集团有限公司", "lon": 113.35, "lat": 23.12, "datestr": "1996年01月08日"}, {"name": "深圳市华超投资控股集团有限公司", "lon": 114.05, "lat": 22.53, "datestr": "1996年05月28日"}, {"name": "恒商电力", "lon": 116.43, "lat": 39.92, "datestr": "1996年06月05日"}, {"name": "卓越置业集团(青岛)有限公司", "lon": 120.38, "lat": 36.08, "datestr": "1996年06月21日"}, {"name": "电子城投资", "lon": 116.43, "lat": 39.92, "datestr": "1996年07月05日"}, {"name": "大金马基础建设", "lon": 121.7, "lat": 39.1, "datestr": "1996年09月28日"}, {"name": "置信实业", "lon": 103.83, "lat": 30.7, "datestr": "1996年10月03日"}, {"name": "星景生态建设投资(苏州)有限公司", "lon": 116.3, "lat": 39.95, "datestr": "1996年11月18日"}, {"name": "广东科达洁能股份有限公司", "lon": 113.3, "lat": 22.8, "datestr": "1996年12月11日"}, {"name": "深圳市城市建设投资发展有限公司", "lon": 113.92, "lat": 22.52, "datestr": "1996年12月19日"}, {"name": "平高集团", "lon": 121.22, "lat": 31.03, "datestr": "1996年12月20日"}, {"name": "上海大生牌业制造有限公司", "lon": 121.12, "lat": 31.15, "datestr": "1997年01月02日"}, {"name": "北京北方空间建筑科技股份有限公司", "lon": 116.43, "lat": 39.92, "datestr": "1997年02月06日"}, {"name": "湖北大都地产集团有限公司", "lon": 114.3, "lat": 30.57, "datestr": "1997年02月28日"}, {"name": "上海弘基企业", "lon": 121.42, "lat": 31.22, "datestr": "1997年03月06日"}, {"name": "上海吉博力房屋卫生设备工程技术有限公司", "lon": 121.27, "lat": 31.38, "datestr": "1997年03月11日"}, {"name": "金程科技", "lon": 120.2, "lat": 30.2, "datestr": "1997年03月22日"}, {"name": "安徽腾越建筑工程有限公司", "lon": 118.27, "lat": 32.1, "datestr": "1997年03月25日"}, {"name": "北京市中宣市政工程有限公司", "lon": 116.28, "lat": 39.85, "datestr": "1997年04月28日"}, {"name": "成富园林", "lon": 104.05, "lat": 30.68, "datestr": "1997年05月23日"}, {"name": "国贸地产", "lon": 118.08, "lat": 24.52, "datestr": "1997年06月03日"}, {"name": "高行投资", "lon": 117.3, "lat": 31.8, "datestr": "1997年06月12日"}, {"name": "深圳市坤宜实业发展有限公司", "lon": 114.27, "lat": 22.73, "datestr": "1997年6月19日"}, {"name": "美涂士建材", "lon": 113.3, "lat": 22.8, "datestr": "1997年07月02日"}, {"name": "江西省第五建设集团有限公司", "lon": 115.87, "lat": 28.67, "datestr": "1997年07月23日"}, {"name": "北洋建材", "lon": 119.93, "lat": 31.75, "datestr": "1997年08月21日"}, {"name": "番禺潮流", "lon": 113.35, "lat": 22.95, "datestr": "1997年08月22日"}, {"name": "青岛鑫源置业集团有限公司", "lon": 120.37, "lat": 36.3, "datestr": "1997年09月10日"}, {"name": "中仁建设集团有限公司", "lon": 114.3, "lat": 30.6, "datestr": "1997年09月17日"}, {"name": "珠海远大置业有限公司", "lon": 113.55, "lat": 22.27, "datestr": "1997年09月25日"}, {"name": "光合文旅控股股份有限公司", "lon": 116.22, "lat": 39.9, "datestr": "1997年10月27日"}, {"name": "青岛隆和置业集团有限公司", "lon": 120.03, "lat": 35.87, "datestr": "1997年10月30日"}, {"name": "重庆金科房地产开发有限公司", "lon": 106.63, "lat": 29.72, "datestr": "1997年11月06日"}, {"name": "金兴建设", "lon": 104.05, "lat": 30.7, "datestr": "1997年11月20日"}, {"name": "青岛瑞源工程集团有限公司", "lon": 120.18, "lat": 35.97, "datestr": "1998年01月07日"}, {"name": "永盛实业", "lon": 110.85, "lat": 21.92, "datestr": "1998年03月10日"}, {"name": "美林控股", "lon": 116.43, "lat": 39.92, "datestr": "1998年03月12日"}, {"name": "嘉特纳幕墙(上海)有限公司", "lon": 121.48, "lat": 31.23, "datestr": "1998年03月18日"}, {"name": "北京市澳际智能消防安全工程有限责任公司", "lon": 116.42, "lat": 39.93, "datestr": "1998年04月08日"}, {"name": "得而达水龙头", "lon": 113.35, "lat": 22.95, "datestr": "1998年04月08日"}, {"name": "永昌路桥集团有限公司", "lon": 116.33, "lat": 35.42, "datestr": "1998年05月18日"}, {"name": "伟星房地产开发", "lon": 121.12, "lat": 28.85, "datestr": "1998年05月21日"}, {"name": "深圳市嘉霖集团有限公司", "lon": 113.92, "lat": 22.52, "datestr": "1998年06月01日"}, {"name": "湖南保利房地产开发", "lon": 112.98, "lat": 28.12, "datestr": "1998年08月04日"}, {"name": "浙江大丰建筑装饰工程有限公司", "lon": 121.15, "lat": 30.03, "datestr": "1998年08月21日"}, {"name": "青岛麦迪绅集团有限公司", "lon": 120.47, "lat": 36.1, "datestr": "1998年09月08日"}, {"name": "腾启房地产", "lon": 104.05, "lat": 30.65, "datestr": "1998年09月25日"}, {"name": "华业地产北京", "lon": 116.43, "lat": 39.92, "datestr": "1998年10月09日"}, {"name": "天津弘泽建设集团有限公司", "lon": 117.15, "lat": 39.13, "datestr": "1998年10月15日"}, {"name": "上海新聚仁物业咨询有限公司", "lon": 121.43, "lat": 31.18, "datestr": "1998年12月14日"}, {"name": "万通地产北京", "lon": 116.43, "lat": 39.92, "datestr": "1998年12月30日"}, {"name": "路域生态", "lon": 116.3, "lat": 39.95, "datestr": "1999年03月30日"}, {"name": "广东立乔交通工程有限公司", "lon": 113.35, "lat": 22.95, "datestr": "1999年05月22日"}, {"name": "中铁四局集团房地产开发有限公司", "lon": 117.3, "lat": 31.8, "datestr": "1999年06月18日"}, {"name": "北京佳益工程咨询有限公司", "lon": 116.37, "lat": 39.92, "datestr": "1999年07月28日"}, {"name": "金中天集团有限公司", "lon": 113.35, "lat": 23.12, "datestr": "1999年09月02日"}, {"name": "南海国际建筑设计", "lon": 113.15, "lat": 23.03, "datestr": "1999年09月13日"}, {"name": "珠海市中广房产开发有限公司", "lon": 113.55, "lat": 22.27, "datestr": "1999年09月17日"}, {"name": "广东东方管业有限公司", "lon": 113.3, "lat": 22.8, "datestr": "1999年10月20日"}, {"name": "北科建集团", "lon": 116.3, "lat": 39.95, "datestr": "1999年11月18日"}, {"name": "荣安集团", "lon": 121.55, "lat": 29.87, "datestr": "1999年11月19日"}, {"name": "辽宁新创集团房地产开发有限公司", "lon": 124.03, "lat": 42.55, "datestr": "2000年01月09日"}, {"name": "重庆三环建设监理咨询有限公司", "lon": 106.48, "lat": 29.48, "datestr": "2000年02月13日"}, {"name": "爱富兰", "lon": 113.27, "lat": 23.13, "datestr": "2000年03月01日"}, {"name": "北京天虹润丰装饰工程有限公司", "lon": 116.28, "lat": 39.85, "datestr": "2000年03月07日"}, {"name": "上海华垒石材", "lon": 121.53, "lat": 31.22, "datestr": "2000年03月09日"}, {"name": "百年城", "lon": 121.58, "lat": 38.9, "datestr": "2000年03月30日"}, {"name": "深圳市蓝盾防水工程有限公司", "lon": 114.05, "lat": 22.53, "datestr": "2000年06月16日"}, {"name": "阜达宏安系统工程", "lon": 116.43, "lat": 39.92, "datestr": "2000年06月20日"}, {"name": "湖北龙腾园林工程有限公司", "lon": 111.35, "lat": 30.65, "datestr": "2000年06月28日"}, {"name": "成都市嘉洲新型防水材料有限公司", "lon": 104.05, "lat": 30.7, "datestr": "2000年06月30日"}, {"name": "北京海淀科技园建设股份有限公司", "lon": 116.3, "lat": 39.95, "datestr": "2000年07月07日"}, {"name": "北京新恒基房地产集团有限公司", "lon": 116.43, "lat": 39.92, "datestr": "2000年07月27日"}, {"name": "名特网络", "lon": 113.35, "lat": 23.12, "datestr": "2000年07月27日"}, {"name": "中建精诚工程咨询有限公司", "lon": 116.37, "lat": 39.92, "datestr": "2000年08月02日"}, {"name": "江苏华利地产集团有限公司", "lon": 119.4, "lat": 32.38, "datestr": "2000年08月08日"}, {"name": "上海喜盈门建材有限公司", "lon": 121.43, "lat": 31.18, "datestr": "2000年8月17日"}, {"name": "上海明佳", "lon": 121.5, "lat": 31.27, "datestr": "2000年08月30日"}, {"name": "上海瑞南企业发展集团有限公司", "lon": 121.38, "lat": 31.12, "datestr": "2000年9月15日"}, {"name": "恒信德龙实业", "lon": 114.27, "lat": 30.55, "datestr": "2000年09月24日"}, {"name": "中天精装", "lon": 114.05, "lat": 22.53, "datestr": "2000年09月28日"}, {"name": "成龙建设集团有限公司", "lon": 120.07, "lat": 29.3, "datestr": "2000年10月27日"}, {"name": "佛山市顺德嘉信置业发展有限公司", "lon": 113.3, "lat": 22.8, "datestr": "2000年11月01日"}, {"name": "东方雨虹防水工程", "lon": 113.35, "lat": 23.12, "datestr": "2000年11月01日"}, {"name": "山东鸿嘉置业有限公司", "lon": 118.08, "lat": 36.97, "datestr": "2001年02月22日"}, {"name": "恒生地产有限公司", "lon": 117.08, "lat": 36.67, "datestr": "2001年02月23日"}, {"name": "大华投资集团", "lon": 118.62, "lat": 32.05, "datestr": "2001年03月14日"}, {"name": "保利地产投资顾问有限公司", "lon": 113.25, "lat": 23.1, "datestr": "2001年03月22日"}, {"name": "鑫远投资", "lon": 112.98, "lat": 28.12, "datestr": "2001年03月27日"}, {"name": "九坤房地产集团有限公司", "lon": 114.3, "lat": 30.57, "datestr": "2001年04月04日"}, {"name": "金宇控股成都", "lon": 104.05, "lat": 30.65, "datestr": "2001年04月11日"}, {"name": "北京紫晶之光科技股份有限公司", "lon": 116.33, "lat": 39.73, "datestr": "2001年04月20日"}, {"name": "灵汇", "lon": 120.13, "lat": 30.32, "datestr": "2001年04月25日"}, {"name": "北京顺华房地产开发有限公司", "lon": 116.65, "lat": 39.92, "datestr": "2001年05月18日"}, {"name": "湖北长江路桥股份有限公司", "lon": 114.32, "lat": 30.35, "datestr": "2001年07月18日"}, {"name": "四川省大家环境艺术工程有限公司", "lon": 104.05, "lat": 30.7, "datestr": "2001年07月31日"}, {"name": "上海创宏建设集团有限公司", "lon": 121.42, "lat": 31.22, "datestr": "2001年08月29日"}, {"name": "中冶", "lon": 116.3, "lat": 39.95, "datestr": "2001年09月05日"}, {"name": "柏利建设", "lon": 116.43, "lat": 39.92, "datestr": "2001年09月06日"}, {"name": "中航建设集团有限公司", "lon": 116.63, "lat": 40.32, "datestr": "2001年09月06日"}, {"name": "浙江北大资源地产有限公司", "lon": 120.13, "lat": 30.27, "datestr": "2001年09月21日"}, {"name": "北京万润投资控股集团有限公司", "lon": 116.42, "lat": 39.93, "datestr": "2001年10月19日"}, {"name": "源程置业上海", "lon": 121.48, "lat": 31.23, "datestr": "2001年11月13日"}, {"name": "肇庆开达五金装饰有限公司", "lon": 112.45, "lat": 23.03, "datestr": "2001年11月23日"}, {"name": "南京明月建设集团有限公司", "lon": 118.85, "lat": 31.95, "datestr": "2001年12月18日"}, {"name": "青房建安", "lon": 120.38, "lat": 36.08, "datestr": "2001年12月18日"}, {"name": "海开房地产", "lon": 116.3, "lat": 39.95, "datestr": "2001年12月28日"}, {"name": "新世纪投资", "lon": 114.27, "lat": 30.55, "datestr": "2002年01月10日"}, {"name": "顺恒利", "lon": 113.9, "lat": 22.57, "datestr": "2002年03月07日"}, {"name": "紫竹高新区", "lon": 121.38, "lat": 31.12, "datestr": "2002年03月11日"}, {"name": "置信房地产开发", "lon": 126.65, "lat": 45.78, "datestr": "2002年03月22日"}, {"name": "光耀集团", "lon": 114.4, "lat": 23.08, "datestr": "2002年04月16日"}, {"name": "瑞明节能科技", "lon": 119.97, "lat": 30.53, "datestr": "2002年04月26日"}, {"name": "河北廊坊中房房地产股份有限公司", "lon": 116.72, "lat": 39.53, "datestr": "2002年06月19日"}, {"name": "北京新颐华卓投资有限公司", "lon": 116.43, "lat": 39.92, "datestr": "2002年07月23日"}, {"name": "南昌市银亿房地产开发有限公司", "lon": 115.93, "lat": 28.55, "datestr": "2002年08月02日"}, {"name": "湖南省中龙集团股份有限公司", "lon": 112.98, "lat": 28.25, "datestr": "2002年08月12日"}, {"name": "吉富绅置业上海", "lon": 121.12, "lat": 31.15, "datestr": "2002年08月14日"}, {"name": "滨江地产", "lon": 117.82, "lat": 30.93, "datestr": "2002年09月05日"}, {"name": "北京顺义新城建设开发有限公司", "lon": 116.43, "lat": 39.92, "datestr": "2002年09月11日"}, {"name": "名居房地产", "lon": 114.05, "lat": 22.53, "datestr": "2002年10月14日"}, {"name": "置沪上海", "lon": 121.48, "lat": 31.4, "datestr": "2002年10月31日"}, {"name": "合乐工程", "lon": 121.48, "lat": 31.23, "datestr": "2002年11月4日"}, {"name": "中铁诺德房地产", "lon": 116.28, "lat": 39.85, "datestr": "2002年11月14日"}, {"name": "深圳鸿洲置业集团有限公司", "lon": 113.92, "lat": 22.52, "datestr": "2002年11月25日"}, {"name": "凯德商用", "lon": 116.43, "lat": 39.92, "datestr": "2002年12月10日"}, {"name": "中铁建工集团诺德投资有限公司", "lon": 114.05, "lat": 22.53, "datestr": "2002年12月16日"}, {"name": "金炜达", "lon": 114.12, "lat": 22.55, "datestr": "2002年12月16日"}, {"name": "新振华房地产", "lon": 113.3, "lat": 22.8, "datestr": "2002年12月23日"}, {"name": "华隆投资", "lon": 114.05, "lat": 22.53, "datestr": "2002年12月26日"}, {"name": "沧州市天成房地产开发有限公司", "lon": 116.85, "lat": 38.32, "datestr": "2003年03月12日"}, {"name": "浙江金厦控股集团", "lon": 119.7, "lat": 29.08, "datestr": "2003年03月14日"}, {"name": "吉利控股", "lon": 113.35, "lat": 23.12, "datestr": "2003年03月24日"}, {"name": "广州市枫源化工有限公司", "lon": 113.83, "lat": 23.3, "datestr": "2003年03月25日"}, {"name": "庄河市新天地商业城有限公司", "lon": 122.98, "lat": 39.7, "datestr": "2003年03月26日"}, {"name": "苏州荣盛房地产开发有限公司", "lon": 120.63, "lat": 31.37, "datestr": "2003年04月14日"}, {"name": "深圳市南山房地产开发有限公司分支机构", "lon": 113.92, "lat": 22.52, "datestr": "2003年05月29日"}, {"name": "广州市吉华勘测股份有限公司", "lon": 113.25, "lat": 23.1, "datestr": "2003年06月04日"}, {"name": "之江置业", "lon": 102.7, "lat": 25.05, "datestr": "2003年06月17日"}, {"name": "肯帝亚木业", "lon": 118.75, "lat": 32.03, "datestr": "2003年06月24日"}, {"name": "万居德实业", "lon": 121.22, "lat": 31.03, "datestr": "2003年07月01日"}, {"name": "上海乔孚舒适家居系统股份有限公司", "lon": 121.38, "lat": 31.12, "datestr": "2003年07月15日"}, {"name": "湖南创远投资集团有限公司", "lon": 112.93, "lat": 28.23, "datestr": "2003年09月02日"}, {"name": "飞翔建筑", "lon": 116.23, "lat": 40.22, "datestr": "2003年09月24日"}, {"name": "波特控股", "lon": 114.12, "lat": 22.55, "datestr": "2003年10月31日"}, {"name": "雄狮景观", "lon": 113.92, "lat": 22.52, "datestr": "2003年12月02日"}, {"name": "笔克旅游", "lon": 114.05, "lat": 22.53, "datestr": "2003年12月25日"}, {"name": "深圳市汇健医疗工程有限公司", "lon": 113.92, "lat": 22.52, "datestr": "2003年12月31日"}, {"name": "北京天瑞金置业投资", "lon": 116.65, "lat": 40.13, "datestr": "2004年01月18日"}, {"name": "中标新亚节能", "lon": 116.3, "lat": 39.95, "datestr": "2004年02月12日"}, {"name": "云南中炬置地集团有限公司", "lon": 102.75, "lat": 25.02, "datestr": "2004年02月17日"}, {"name": "浙江英冠控股集团有限公司", "lon": 120.27, "lat": 30.17, "datestr": "2004年02月26日"}, {"name": "京汇美饰建筑工程", "lon": 113.35, "lat": 23.12, "datestr": "2004年3月15日"}, {"name": "上海亚泽新型屋面系统股份有限公司", "lon": 121.47, "lat": 30.92, "datestr": "2004年04月01日"}, {"name": "上海同砚", "lon": 121.52, "lat": 31.27, "datestr": "2004年04月02日"}, {"name": "北大资源集团", "lon": 116.3, "lat": 39.95, "datestr": "2004年06月02日"}, {"name": "湖南珠江实业投资有限公司", "lon": 112.98, "lat": 28.25, "datestr": "2004年06月08日"}, {"name": "深圳市天朝实业有限公司", "lon": 114.27, "lat": 22.73, "datestr": "2004年06月17日"}, {"name": "北京嘉复欣科技", "lon": 116.3, "lat": 39.95, "datestr": "2004年07月02日"}, {"name": "成道建设(中国)有限公司", "lon": 121.38, "lat": 31.12, "datestr": "2004年07月09日"}, {"name": "北京顺安盛消防", "lon": 116.43, "lat": 39.92, "datestr": "2004年07月30日"}, {"name": "上海旭密林幕墙有限公司", "lon": 121.43, "lat": 31.18, "datestr": "2004年08月02日"}, {"name": "大汉物流股份有限公司", "lon": 113.03, "lat": 28.18, "datestr": "2004年08月06日"}, {"name": "北京环洋经典展柜制造有限公司", "lon": 116.3, "lat": 39.95, "datestr": "2004年08月10日"}, {"name": "湖北大汉隆城投资开发集团有限公司", "lon": 114.3, "lat": 30.57, "datestr": "2004年09月03日"}, {"name": "东凌房地产", "lon": 113.83, "lat": 23.3, "datestr": "2004年09月22日"}, {"name": "招商局地产(武汉)有限公司", "lon": 114.27, "lat": 30.55, "datestr": "2004年10月12日"}, {"name": "金渝建设工程", "lon": 106.63, "lat": 29.72, "datestr": "2004年10月18日"}, {"name": "绿茵天地体育产业股份有限公司", "lon": 116.43, "lat": 39.92, "datestr": "2004年10月22日"}, {"name": "中庆建设有限责任公司", "lon": 125.25, "lat": 43.88, "datestr": "2004年10月27日"}, {"name": "中弘卓业集团有限公司", "lon": 116.43, "lat": 39.92, "datestr": "2004年11月04日"}, {"name": "劲嘉房地产深圳", "lon": 113.92, "lat": 22.52, "datestr": "2004年12月08日"}, {"name": "宁波建工股份有限公司", "lon": 121.53, "lat": 29.83, "datestr": "2004年12月20日"}, {"name": "沈阳维丽雅园林景观工程有限公司", "lon": 123.4, "lat": 41.78, "datestr": "2005年01月05日"}, {"name": "北京三月雨文化传播有限责任公司", "lon": 116.3, "lat": 39.95, "datestr": "2005年01月18日"}, {"name": "江山多娇房地产", "lon": 106.57, "lat": 29.52, "datestr": "2005年02月04日"}, {"name": "上海中森建筑与工程设计顾问有限公司", "lon": 121.4, "lat": 31.25, "datestr": "2005年2月5日"}, {"name": "上海城投悦城置业", "lon": 121.52, "lat": 31.27, "datestr": "2005年02月06日"}, {"name": "江苏省住建集团有限公司", "lon": 118.78, "lat": 32.03, "datestr": "2005年03月03日"}, {"name": "河南怡丰置业发展有限公司", "lon": 116.37, "lat": 39.92, "datestr": "2005年03月08日"}, {"name": "博思格建筑钢结构广州", "lon": 113.45, "lat": 23.1, "datestr": "2005年03月18日"}, {"name": "桑叶建筑", "lon": 121.42, "lat": 31.22, "datestr": "2005年3月22日"}, {"name": "北京市京港汇丰空调制冷设备有限责任公司", "lon": 116.43, "lat": 39.92, "datestr": "2005年03月30日"}, {"name": "祝桥新镇", "lon": 121.53, "lat": 31.22, "datestr": "2005年04月04日"}, {"name": "华盛智地", "lon": 114.05, "lat": 22.53, "datestr": "2005年04月06日"}, {"name": "廊坊益田房地产开发有限公司", "lon": 116.5, "lat": 39.32, "datestr": "2005年04月12日"}, {"name": "中驰集团", "lon": 121.38, "lat": 31.12, "datestr": "2005年5月10日"}, {"name": "大连驰敖集团有限公司", "lon": 121.57, "lat": 38.95, "datestr": "2005年05月17日"}, {"name": "新华联置地", "lon": 116.43, "lat": 39.92, "datestr": "2005年06月23日"}, {"name": "华南实业", "lon": 113.15, "lat": 23.03, "datestr": "2005年07月13日"}, {"name": "云南西泰电线电缆有限公司", "lon": 102.75, "lat": 25.02, "datestr": "2005年07月28日"}, {"name": "四川汇日央扩置业有限公司", "lon": 104.05, "lat": 30.65, "datestr": "2005年08月02日"}, {"name": "武汉瑞安天地房地产发展有限公司分支机构", "lon": 114.3, "lat": 30.6, "datestr": "2005年08月02日"}, {"name": "人和新天地", "lon": 113.23, "lat": 23.13, "datestr": "2005年08月03日"}, {"name": "上海中电", "lon": 120.13, "lat": 30.32, "datestr": "2005年08月23日"}, {"name": "复地房地产", "lon": 112.98, "lat": 28.25, "datestr": "2005年09月12日"}, {"name": "青岛政建投资集团", "lon": 120.37, "lat": 36.3, "datestr": "2005年10月20日"}, {"name": "长兴伊通有限公司", "lon": 119.9, "lat": 31.02, "datestr": "2005年11月01日"}, {"name": "凯联达", "lon": 114.12, "lat": 22.55, "datestr": "2005年11月22日"}, {"name": "北京利建恒高新技术有限公司", "lon": 116.28, "lat": 39.85, "datestr": "2005年11月30日"}, {"name": "中贸房地产开发", "lon": 108.93, "lat": 34.23, "datestr": "2005年12月05日"}, {"name": "北京方法科技发展有限公司", "lon": 116.3, "lat": 39.95, "datestr": "2005年12月06日"}, {"name": "融侨房地产", "lon": 113.73, "lat": 34.4, "datestr": "2006年01月10日"}, {"name": "江苏东建投资建设有限公司", "lon": 120.63, "lat": 31.37, "datestr": "2006年02月13日"}, {"name": "杭州元创新型材料科技有限公司", "lon": 120.2, "lat": 30.2, "datestr": "2006年03月07日"}, {"name": "华润新鸿基", "lon": 120.27, "lat": 31.57, "datestr": "2006年03月15日"}, {"name": "致道园林工程", "lon": 118.78, "lat": 32.03, "datestr": "2006年04月11日"}, {"name": "正佳投资集团有限公司", "lon": 120.13, "lat": 30.27, "datestr": "2006年07月05日"}, {"name": "重庆恒大", "lon": 106.63, "lat": 29.72, "datestr": "2006年07月17日"}, {"name": "湖北恒大", "lon": 115.07, "lat": 30.23, "datestr": "2006年07月20日"}, {"name": "深圳市威尔地坪材料有限公司", "lon": 113.9, "lat": 22.57, "datestr": "2006年9月13日"}, {"name": "北京住宏建筑装饰工程有限公司", "lon": 116.43, "lat": 39.92, "datestr": "2006年11月03日"}, {"name": "浙大网新置地", "lon": 120.2, "lat": 30.2, "datestr": "2006年11月14日"}, {"name": "法莱科技", "lon": 120.2, "lat": 30.27, "datestr": "2006年12月13日"}, {"name": "铭泰集团", "lon": 113.55, "lat": 22.27, "datestr": "2006年12月22日"}, {"name": "福建中意铁科新型材料有限公司", "lon": 116.35, "lat": 25.83, "datestr": "2007年01月10日"}, {"name": "吉兴隆集团", "lon": 102.67, "lat": 25.03, "datestr": "2007年01月23日"}, {"name": "鸿曦房地产", "lon": 106.25, "lat": 38.47, "datestr": "2007年3月9日"}, {"name": "华润置地(沈阳)有限公司", "lon": 123.4, "lat": 41.78, "datestr": "2007年03月14日"}, {"name": "新兴发展集团有限公司", "lon": 116.43, "lat": 39.92, "datestr": "2007年03月15日"}, {"name": "笛东", "lon": 116.43, "lat": 39.92, "datestr": "2007年03月23日"}, {"name": "广州东企房地产开发有限公司", "lon": 113.35, "lat": 23.12, "datestr": "2007年03月27日"}, {"name": "内蒙古海亮房地产开发有限公司", "lon": 111.6, "lat": 40.8, "datestr": "2007年04月11日"}, {"name": "创一佳", "lon": 118.75, "lat": 32.03, "datestr": "2007年04月30日"}, {"name": "山东秦恒建筑节能工程有限公司", "lon": 117.08, "lat": 36.67, "datestr": "2007年05月25日"}, {"name": "广州市番禺创新科技园有限公司", "lon": 113.35, "lat": 22.95, "datestr": "2007年05月28日"}, {"name": "广州震雄装饰工程有限公司", "lon": 113.35, "lat": 23.12, "datestr": "2007年05月30日"}, {"name": "宏泰房地产", "lon": 118.32, "lat": 33.95, "datestr": "2007年06月05日"}, {"name": "深圳市鹏瑞地产开发有限公司", "lon": 113.92, "lat": 22.52, "datestr": "2007年06月05日"}, {"name": "中交物产集团有限公司", "lon": 120.2, "lat": 30.27, "datestr": "2007年06月05日"}, {"name": "武汉九立投资集团有限公司", "lon": 114.3, "lat": 30.6, "datestr": "2007年06月25日"}, {"name": "金秋控股集团有限公司", "lon": 116.3, "lat": 39.95, "datestr": "2007年07月04日"}, {"name": "左尚明舍家居用品(上海)有限公司", "lon": 121.47, "lat": 30.92, "datestr": "2007年07月17日"}, {"name": "大卫房地产", "lon": 120.73, "lat": 28.87, "datestr": "2007年07月24日"}, {"name": "开辉实业", "lon": 119.3, "lat": 26.07, "datestr": "2007年08月03日"}, {"name": "北京鼎峰地产投资顾问有限公司", "lon": 116.43, "lat": 39.92, "datestr": "2007年08月06日"}, {"name": "成都保利", "lon": 104.05, "lat": 30.65, "datestr": "2007年08月22日"}, {"name": "东方银座集团", "lon": 114.05, "lat": 22.53, "datestr": "2007年08月27日"}, {"name": "南京国聪科技发展有限公司", "lon": 118.85, "lat": 31.95, "datestr": "2007年09月21日"}, {"name": "中南幕墙", "lon": 120.2, "lat": 30.2, "datestr": "2007年09月24日"}, {"name": "湖北九州通置业发展有限公司", "lon": 114.27, "lat": 30.55, "datestr": "2007年10月15日"}, {"name": "中维国际工程设计有限公司", "lon": 104.05, "lat": 30.65, "datestr": "2007年11月02日"}, {"name": "和记黄埔地产(武汉)", "lon": 114.3, "lat": 30.57, "datestr": "2007年11月21日"}, {"name": "正宏置业集团", "lon": 116.23, "lat": 40.22, "datestr": "2007年11月29日"}, {"name": "中信正业投资", "lon": 116.43, "lat": 39.92, "datestr": "2007年12月03日"}, {"name": "浙江南方装饰工程有限公司", "lon": 120.13, "lat": 30.27, "datestr": "2007年12月14日"}, {"name": "荣尧智慧", "lon": 117.2, "lat": 39.12, "datestr": "2007年12月20日"}, {"name": "洛阳天城房地产开发有限公司", "lon": 112.43, "lat": 34.67, "datestr": "2008年01月11日"}, {"name": "京汉置业集团", "lon": 116.22, "lat": 39.9, "datestr": "2008年02月01日"}, {"name": "朵纳卫浴", "lon": 121.12, "lat": 28.85, "datestr": "2008年02月02日"}, {"name": "福威建材", "lon": 114.52, "lat": 38.05, "datestr": "2008年3月11日"}, {"name": "中亚置业集团", "lon": 113.92, "lat": 22.52, "datestr": "2008年3月18日"}, {"name": "上海恒润数字科技有限公司", "lon": 121.47, "lat": 30.92, "datestr": "2008年03月21日"}, {"name": "森磊源", "lon": 113.92, "lat": 22.52, "datestr": "2008年03月28日"}, {"name": "瀚涧康体", "lon": 113.27, "lat": 23.17, "datestr": "2008年04月15日"}, {"name": "南京中山园林古瑞建设有限责任公司", "lon": 118.8, "lat": 32.05, "datestr": "2008年06月13日"}, {"name": "地峰", "lon": 113.92, "lat": 22.52, "datestr": "2008年6月19日"}, {"name": "大连万科置业有限公司", "lon": 121.57, "lat": 38.95, "datestr": "2008年07月14日"}, {"name": "阿特贝尔", "lon": 121.52, "lat": 31.27, "datestr": "2008年07月25日"}, {"name": "邢台中鼎麒麟房地产开发有限公司", "lon": 114.47, "lat": 37.05, "datestr": "2008年7月29日"}, {"name": "北京绿宸控股集团有限公司", "lon": 116.3, "lat": 39.95, "datestr": "2008年09月05日"}, {"name": "天津皇冠幕墙装饰股份有限公司", "lon": 117.03, "lat": 39.38, "datestr": "2008年11月10日"}, {"name": "广丰集团有限公司", "lon": 114.4, "lat": 23.08, "datestr": "2008年11月12日"}, {"name": "上海嘉来", "lon": 121.5, "lat": 31.27, "datestr": "2008年11月17日"}, {"name": "成都康洁水务有限公司", "lon": 104.05, "lat": 30.7, "datestr": "2008年11月25日"}, {"name": "远大置业集团有限责任公司", "lon": 116.43, "lat": 39.92, "datestr": "2008年12月01日"}, {"name": "成信建业节能", "lon": 121.38, "lat": 31.12, "datestr": "2008年12月10日"}, {"name": "深圳市金地楼宇工程有限公司", "lon": 113.92, "lat": 22.52, "datestr": "2008年12月16日"}, {"name": "上海中暨投资管理有限公司", "lon": 121.27, "lat": 31.38, "datestr": "2008年12月22日"}, {"name": "浙江春明防水建材有限公司", "lon": 120.95, "lat": 30.53, "datestr": "2009年01月09日"}, {"name": "万锦置业", "lon": 112.95, "lat": 27.78, "datestr": "2009年01月20日"}, {"name": "凯丹置地", "lon": 116.43, "lat": 39.92, "datestr": "2009年02月04日"}, {"name": "湖北恒泰天纵控股集团有限公司", "lon": 114.27, "lat": 30.6, "datestr": "2009年03月04日"}, {"name": "深圳市合泰地产集团有限公司", "lon": 114.05, "lat": 22.53, "datestr": "2009年03月06日"}, {"name": "湖南棕榈浔龙河生态城镇发展有限公司", "lon": 113.07, "lat": 28.25, "datestr": "2009年03月11日"}, {"name": "嘉兴创新园发展有限公司", "lon": 120.7, "lat": 30.77, "datestr": "2009年03月16日"}, {"name": "上海直玖机场设备有限公司", "lon": 116.43, "lat": 39.92, "datestr": "2009年4月8日"}, {"name": "深圳华瑞达装饰集团有限公司", "lon": 114.05, "lat": 22.53, "datestr": "2009年4月14日"}, {"name": "深圳市富驰房地产开发有限公司", "lon": 114.12, "lat": 22.55, "datestr": "2009年4月30日"}, {"name": "青岛仁洲控股集团有限公司", "lon": 120.38, "lat": 36.07, "datestr": "2009年05月04日"}, {"name": "漳州中扬房地产开发有限公司", "lon": 117.65, "lat": 24.52, "datestr": "2009年05月12日"}, {"name": "诺菲博尔建材销售(北京)有限公司", "lon": 116.43, "lat": 39.92, "datestr": "2009年05月25日"}, {"name": "港龙控股集团有限公司", "lon": 120.63, "lat": 31.27, "datestr": "2009年06月17日"}, {"name": "大连恒隆地产有限公司", "lon": 121.6, "lat": 38.92, "datestr": "2009年06月19日"}, {"name": "珠海航空城", "lon": 113.4, "lat": 22.07, "datestr": "2009年07月02日"}, {"name": "东亚信元", "lon": 120.27, "lat": 31.9, "datestr": "2009年08月06日"}, {"name": "赣州市峰山投资开发有限公司", "lon": 114.93, "lat": 25.87, "datestr": "2009年08月11日"}, {"name": "美特耐新型建材(广州)有限公司", "lon": 113.27, "lat": 23.13, "datestr": "2009年08月24日"}, {"name": "中国供销农产品批发市场控股有限公司", "lon": 116.37, "lat": 39.92, "datestr": "2009年09月07日"}, {"name": "山东亿丰实业集团有限公司", "lon": 118.47, "lat": 36.68, "datestr": "2009年09月08日"}, {"name": "南京银城房地产开发有限公司", "lon": 118.77, "lat": 32.07, "datestr": "2009年09月24日"}, {"name": "鸿图建筑", "lon": 121.43, "lat": 31.18, "datestr": "2009年9月28日"}, {"name": "广东光华天裕集团有限公司", "lon": 113.35, "lat": 23.12, "datestr": "2009年10月20日"}, {"name": "北京联合荣大建材有限公司", "lon": 116.63, "lat": 40.32, "datestr": "2009年10月21日"}, {"name": "深圳市颐安投资集团有限公司", "lon": 113.92, "lat": 22.52, "datestr": "2009年11月24日"}, {"name": "愿景集团", "lon": 103.67, "lat": 30.63, "datestr": "2009年12月02日"}, {"name": "中核华泰建设有限公司", "lon": 113.92, "lat": 22.52, "datestr": "2009年12月23日"}, {"name": "广州市荔园置业发展集团有限公司", "lon": 113.35, "lat": 22.95, "datestr": "2009年12月24日"}, {"name": "金宝厦建筑", "lon": 116.43, "lat": 39.92, "datestr": "2009年12月25日"}, {"name": "瑞信实业", "lon": 104.08, "lat": 30.67, "datestr": "2010年01月06日"}, {"name": "桑田智能工程技术(上海)有限公司", "lon": 121.4, "lat": 31.25, "datestr": "2010年01月11日"}, {"name": "济南恒大绿洲置业有限公司", "lon": 117.07, "lat": 36.68, "datestr": "2010年01月18日"}, {"name": "联合中邦", "lon": 119.03, "lat": 33.58, "datestr": "2010年01月27日"}, {"name": "高和安养投资管理(北京)有限公司", "lon": 116.3, "lat": 39.95, "datestr": "2010年01月29日"}, {"name": "山东宏海置业", "lon": 117.07, "lat": 36.68, "datestr": "2010年02月02日"}, {"name": "新怡和控股", "lon": 115.68, "lat": 32.18, "datestr": "2010年03月03日"}, {"name": "福建融鼎房地产开发有限责任公司", "lon": 119.38, "lat": 25.72, "datestr": "2010年03月09日"}, {"name": "常州龙城韩利壁衣有限公司", "lon": 119.97, "lat": 31.83, "datestr": "2010年03月26日"}, {"name": "深圳市瑞捷建筑工程咨询有限公司", "lon": 114.05, "lat": 22.53, "datestr": "2010年04月12日"}, {"name": "邛崃市建设投资集团有限公司", "lon": 103.47, "lat": 30.42, "datestr": "2010年5月17日"}, {"name": "上海赢越装饰设计工程有限公司", "lon": 121.53, "lat": 31.22, "datestr": "2010年05月29日"}, {"name": "湖南大自然投资集团有限公司", "lon": 113.15, "lat": 27.83, "datestr": "2010年06月01日"}, {"name": "万呈集团有限公司", "lon": 116.3, "lat": 39.95, "datestr": "2010年06月04日"}, {"name": "深圳瀚康控股集团有限公司", "lon": 114.05, "lat": 22.53, "datestr": "2010年6月7日"}, {"name": "株洲市美的房地产发展有限公司", "lon": 113.03, "lat": 28.18, "datestr": "2010年06月10日"}, {"name": "南京博盈装饰材料有限公司", "lon": 118.75, "lat": 32.03, "datestr": "2010年07月12日"}, {"name": "上海尚远建筑安装有限公司", "lon": 121.53, "lat": 31.22, "datestr": "2010年7月16日"}, {"name": "上海东岸建筑设计事务所有限公司", "lon": 121.52, "lat": 31.27, "datestr": "2010年8月10日"}, {"name": "银泰置地商业", "lon": 116.43, "lat": 39.92, "datestr": "2010年09月17日"}, {"name": "庭瑞", "lon": 114.27, "lat": 30.6, "datestr": "2010年09月30日"}, {"name": "湖北小蚂蚁金刚石工具有限公司", "lon": 115.93, "lat": 30.08, "datestr": "2010年10月22日"}, {"name": "天下石仓(天津)有限公司", "lon": 117.03, "lat": 39.38, "datestr": "2010年10月27日"}, {"name": "际华置业", "lon": 113.1, "lat": 29.37, "datestr": "2010年11月01日"}, {"name": "青岛国誉房地产开发有限公司(分支机构)", "lon": 120.38, "lat": 36.08, "datestr": "2010年11月15日"}, {"name": "重庆名流置业有限公司", "lon": 106.4, "lat": 29.8, "datestr": "2010年11月23日"}, {"name": "莘天置业", "lon": 121.38, "lat": 31.12, "datestr": "2010年12月01日"}, {"name": "艾肯联合", "lon": 121.45, "lat": 31.23, "datestr": "2010年12月15日"}, {"name": "中建国际投资(中国)有限公司", "lon": 113.92, "lat": 22.52, "datestr": "2010年12月20日"}, {"name": "滁州国金实业有限公司", "lon": 118.3, "lat": 32.32, "datestr": "2010年12月20日"}, {"name": "盈创置地", "lon": 116.43, "lat": 39.92, "datestr": "2010年12月23日"}, {"name": "鼎标建筑", "lon": 104.05, "lat": 30.7, "datestr": "2010年12月30日"}, {"name": "深圳市银德投资控股有限公司", "lon": 113.92, "lat": 22.52, "datestr": "2011年01月12日"}, {"name": "房开控股北京", "lon": 116.13, "lat": 39.75, "datestr": "2011年01月25日"}, {"name": "中农国信", "lon": 116.43, "lat": 39.92, "datestr": "2011年02月10日"}, {"name": "和记黄埔南京", "lon": 118.75, "lat": 32.03, "datestr": "2011年02月21日"}, {"name": "中交地产", "lon": 116.37, "lat": 39.92, "datestr": "2011年03月03日"}, {"name": "盘锦大业建筑工程有限公司", "lon": 122.02, "lat": 41.25, "datestr": "2011年03月10日"}, {"name": "南京启迪科技园发展有限公司", "lon": 118.85, "lat": 31.95, "datestr": "2011年03月11日"}, {"name": "一涵投资", "lon": 120.27, "lat": 31.57, "datestr": "2011年03月16日"}, {"name": "丰达利", "lon": 118.88, "lat": 32.12, "datestr": "2011年03月24日"}, {"name": "深圳市泰丰投资集团有限公司", "lon": 114.05, "lat": 22.53, "datestr": "2011年04月13日"}, {"name": "华恒兴业", "lon": 116.65, "lat": 39.92, "datestr": "2011年04月27日"}, {"name": "孝感协丰置业有限公司", "lon": 113.92, "lat": 30.92, "datestr": "2011年04月28日"}, {"name": "一达国际", "lon": 116.28, "lat": 39.85, "datestr": "2011年05月26日"}, {"name": "哥伦布商业", "lon": 121.42, "lat": 31.22, "datestr": "2011年05月30日"}, {"name": "兴一实业", "lon": 114.12, "lat": 22.55, "datestr": "2011年06月03日"}, {"name": "绿城东方建设管理有限公司", "lon": 118.75, "lat": 32.03, "datestr": "2011年07月12日"}, {"name": "上海古胤", "lon": 121.38, "lat": 31.12, "datestr": "2011年09月02日"}, {"name": "浙江盾基建材有限公司", "lon": 120.13, "lat": 30.27, "datestr": "2011年09月09日"}, {"name": "海亮七大洲", "lon": 120.23, "lat": 29.72, "datestr": "2011年09月15日"}, {"name": "盛源集团", "lon": 121.43, "lat": 31.18, "datestr": "2011年09月15日"}, {"name": "广东信业地产集团有限公司", "lon": 113.35, "lat": 22.95, "datestr": "2011年09月29日"}, {"name": "北京新都昌控股集团有限公司", "lon": 116.43, "lat": 39.92, "datestr": "2011年10月21日"}, {"name": "中邺集团有限公司", "lon": 104.1, "lat": 30.67, "datestr": "2011年12月5日"}, {"name": "北京筑巢投资", "lon": 116.43, "lat": 39.92, "datestr": "2011年12月08日"}, {"name": "北京雅林士博建筑工程有限公司", "lon": 116.22, "lat": 39.9, "datestr": "2011年12月19日"}, {"name": "南德经济发展集团", "lon": 114.3, "lat": 30.6, "datestr": "2011年12月20日"}, {"name": "攀枝花市花城投资有限责任公司", "lon": 101.73, "lat": 26.5, "datestr": "2011年12月21日"}, {"name": "金谷房地产", "lon": 113.15, "lat": 27.83, "datestr": "2012年01月10日"}, {"name": "佛山南海保利海荣投资", "lon": 113.15, "lat": 23.03, "datestr": "2012年01月11日"}, {"name": "河北保利房地产开发有限公司", "lon": 114.47, "lat": 38.03, "datestr": "2012年01月12日"}, {"name": "江苏泰乐城医疗投资股份有限公司", "lon": 118.75, "lat": 32.03, "datestr": "2012年02月13日"}, {"name": "深圳恒邦伟业投资集团有限公司", "lon": 114.05, "lat": 22.53, "datestr": "2012年2月17日"}, {"name": "远东幕墙", "lon": 113.9, "lat": 22.57, "datestr": "2012年03月22日"}, {"name": "思睿地产", "lon": 104.05, "lat": 30.65, "datestr": "2012年03月26日"}, {"name": "甘肃鼎晟智能工程有限公司", "lon": 103.83, "lat": 36.05, "datestr": "2012年03月28日"}, {"name": "浙江中服", "lon": 120.23, "lat": 29.28, "datestr": "2012年05月07日"}, {"name": "燕广置业", "lon": 116.37, "lat": 39.92, "datestr": "2012年05月07日"}, {"name": "北京佰惠嘉房地产顾问有限公司", "lon": 116.43, "lat": 39.92, "datestr": "2012年05月17日"}, {"name": "甘肃通宇建筑工程", "lon": 104.62, "lat": 35.58, "datestr": "2012年05月29日"}, {"name": "广州行盛", "lon": 113.45, "lat": 23.1, "datestr": "2012年06月01日"}, {"name": "堡密特建筑材料", "lon": 121.53, "lat": 31.22, "datestr": "2012年06月18日"}, {"name": "遵义汇川广信房地产开发有限责任公司", "lon": 106.92, "lat": 27.65, "datestr": "2012年07月02日"}, {"name": "青年乐", "lon": 116.43, "lat": 39.92, "datestr": "2012年07月04日"}, {"name": "苏州市木渎惠润汽车产业园发展有限公司", "lon": 120.63, "lat": 31.27, "datestr": "2012年07月12日"}, {"name": "嘉兆控股", "lon": 120.2, "lat": 30.27, "datestr": "2012年08月09日"}, {"name": "万德置业", "lon": 118.62, "lat": 35.78, "datestr": "2012年08月21日"}, {"name": "中海宏洋地产", "lon": 114.93, "lat": 25.87, "datestr": "2012年08月23日"}, {"name": "城格投资", "lon": 118.75, "lat": 32.03, "datestr": "2012年09月03日"}, {"name": "江苏证大商业文化发展有限公司", "lon": 118.77, "lat": 32.0, "datestr": "2012年09月04日"}, {"name": "沣东市政工程", "lon": 108.93, "lat": 34.28, "datestr": "2012年10月24日"}, {"name": "天津市富都房地产开发有限公司", "lon": 117.22, "lat": 39.12, "datestr": "2012年10月26日"}, {"name": "鑫海汇投资", "lon": 102.67, "lat": 25.03, "datestr": "2012年11月5日"}, {"name": "通谊投资", "lon": 117.22, "lat": 39.12, "datestr": "2012年11月5日"}, {"name": "北冰洋投资集团", "lon": 114.13, "lat": 30.62, "datestr": "2012年11月19日"}, {"name": "优品道置地", "lon": 104.05, "lat": 30.68, "datestr": "2012年11月21日"}, {"name": "东方汉世陶瓷(北京)有限公司", "lon": 116.23, "lat": 40.22, "datestr": "2012年11月28日"}, {"name": "天业亘源房地产", "lon": 120.47, "lat": 36.1, "datestr": "2012年11月29日"}, {"name": "相原集团", "lon": 120.2, "lat": 30.27, "datestr": "2012年12月13日"}, {"name": "星融置业", "lon": 119.38, "lat": 25.72, "datestr": "2012年12月26日"}, {"name": "深圳市金中泰环保节能科技有限公司", "lon": 114.05, "lat": 22.53, "datestr": "2012年12月26日"}, {"name": "山东融利银谷置业", "lon": 117.57, "lat": 34.87, "datestr": "2013年01月06日"}, {"name": "上海钰翔投资控股集团有限公司", "lon": 121.5, "lat": 31.27, "datestr": "2013年1月30日"}, {"name": "捷运房地产", "lon": 120.35, "lat": 31.6, "datestr": "2013年02月01日"}, {"name": "南充绿地申川置业有限公司", "lon": 106.08, "lat": 30.78, "datestr": "2013年3月5日"}, {"name": "广州帕特森建筑设计有限公司", "lon": 113.27, "lat": 23.13, "datestr": "2013年03月06日"}, {"name": "天津鸿盛投资集团有限公司", "lon": 117.03, "lat": 39.38, "datestr": "2013年03月11日"}, {"name": "深圳市泰富华天峦湖置业有限公司", "lon": 113.92, "lat": 22.52, "datestr": "2013年03月13日"}, {"name": "杭州拱墅万达投资有限公司", "lon": 120.13, "lat": 30.32, "datestr": "2013年03月22日"}, {"name": "上海宾孚建设工程顾问有限公司", "lon": 121.42, "lat": 31.22, "datestr": "2013年3月25日"}, {"name": "湖北汇康汇美工程技术有限责任公司", "lon": 114.33, "lat": 30.5, "datestr": "2013年03月26日"}, {"name": "中投地产", "lon": 112.6, "lat": 26.9, "datestr": "2013年04月01日"}, {"name": "远成置业", "lon": 105.57, "lat": 30.52, "datestr": "2013年04月10日"}, {"name": "中交机电工程局", "lon": 116.37, "lat": 39.92, "datestr": "2013年04月16日"}, {"name": "北京录科立福电梯科技服务有限公司", "lon": 116.43, "lat": 39.92, "datestr": "2013年05月16日"}, {"name": "长沙蓝光和骏置业有限公司", "lon": 112.98, "lat": 28.12, "datestr": "2013年05月20日"}, {"name": "上海青庭新地置业有限公司", "lon": 121.38, "lat": 31.12, "datestr": "2013年05月30日"}, {"name": "中航里城", "lon": 113.92, "lat": 22.52, "datestr": "2013年06月08日"}, {"name": "江苏金材科技有限公司", "lon": 119.43, "lat": 32.38, "datestr": "2013年06月21日"}, {"name": "核诚建筑", "lon": 121.38, "lat": 31.12, "datestr": "2013年06月26日"}, {"name": "佳莲控股", "lon": 116.3, "lat": 39.95, "datestr": "2013年06月26日"}, {"name": "杭州拓江置业有限公司", "lon": 120.2, "lat": 30.27, "datestr": "2013年07月22日"}, {"name": "河南同元文化古镇旅游开发有限公司", "lon": 112.45, "lat": 34.62, "datestr": "2013年07月23日"}, {"name": "深圳市龙岗区产业投资服务集团有限公司", "lon": 114.27, "lat": 22.73, "datestr": "2013年08月06日"}, {"name": "中新房装饰", "lon": 116.37, "lat": 39.92, "datestr": "2013年08月09日"}, {"name": "紫城资产", "lon": 116.43, "lat": 39.92, "datestr": "2013年08月14日"}, {"name": "荆州竹叶山商贸城", "lon": 112.18, "lat": 30.35, "datestr": "2013年08月15日"}, {"name": "南京莱蒙水榭花都房地产", "lon": 118.75, "lat": 32.03, "datestr": "2013年09月03日"}, {"name": "青海万江房地产开发有限公司", "lon": 101.27, "lat": 36.68, "datestr": "2013年09月11日"}, {"name": "嘉凯城集团城镇化建设发展有限公司", "lon": 120.13, "lat": 30.27, "datestr": "2013年09月16日"}, {"name": "广东朗润集团有限公司", "lon": 113.27, "lat": 23.13, "datestr": "2013年9月23日"}, {"name": "吴钢建材", "lon": 119.32, "lat": 26.08, "datestr": "2013年09月30日"}, {"name": "恒河控股有限公司", "lon": 104.1, "lat": 30.67, "datestr": "2013年10月16日"}, {"name": "济南东城帝华房地产开发有限公司", "lon": 117.08, "lat": 36.67, "datestr": "2013年11月01日"}, {"name": "明炜集团", "lon": 114.05, "lat": 22.53, "datestr": "2013年11月04日"}, {"name": "武汉当代海洋置业股份有限公司", "lon": 114.3, "lat": 30.57, "datestr": "2013年11月06日"}, {"name": "章丘立天唐人置业有限公司", "lon": 117.53, "lat": 36.72, "datestr": "2013年11月20日"}, {"name": "四川南鑫物流集团有限公司", "lon": 106.1, "lat": 30.77, "datestr": "2013年11月20日"}, {"name": "苏州吴中万达广场", "lon": 120.63, "lat": 31.27, "datestr": "2013年11月27日"}, {"name": "勒泰商业管理", "lon": 116.43, "lat": 39.92, "datestr": "2013年12月19日"}, {"name": "南通万达", "lon": 120.8, "lat": 32.03, "datestr": "2013年12月23日"}, {"name": "黄石浙楚企业港发展有限公司", "lon": 114.3, "lat": 30.57, "datestr": "2014年01月08日"}, {"name": "洲业投资(上海)有限公司", "lon": 121.43, "lat": 31.18, "datestr": "2014年1月14日"}, {"name": "国奥北方投资发展有限公司", "lon": 123.95, "lat": 47.35, "datestr": "2014年01月17日"}, {"name": "济南荣恩房地产开发有限公司", "lon": 117.07, "lat": 36.68, "datestr": "2014年01月28日"}, {"name": "优暖家地", "lon": 121.27, "lat": 31.38, "datestr": "2014年02月07日"}, {"name": "深圳市辉建地产开发有限公司", "lon": 114.05, "lat": 22.53, "datestr": "2014年2月19日"}, {"name": "盘锦万达广场置业有限公司", "lon": 122.07, "lat": 41.12, "datestr": "2014年03月18日"}, {"name": "上海梦中心文化传媒有限公司", "lon": 121.43, "lat": 31.18, "datestr": "2014年3月19日"}, {"name": "喜来山资产管理(上海)有限公司", "lon": 121.48, "lat": 31.23, "datestr": "2014年3月19日"}, {"name": "青岛同致富达商业经营管理有限公司", "lon": 120.37, "lat": 36.3, "datestr": "2014年03月26日"}, {"name": "北京中弘网络营销顾问有限公司", "lon": 116.43, "lat": 39.92, "datestr": "2014年04月25日"}, {"name": "青岛市中纺四季青实业股份有限公司", "lon": 120.45, "lat": 36.38, "datestr": "2014年04月30日"}, {"name": "龙和投资", "lon": 112.13, "lat": 32.03, "datestr": "2014年05月14日"}, {"name": "资阳万达广场投资有限公司", "lon": 104.65, "lat": 30.12, "datestr": "2014年05月23日"}, {"name": "正东投资", "lon": 116.92, "lat": 38.93, "datestr": "2014年06月04日"}, {"name": "桃江现代竹产业科技园运营有限公司", "lon": 112.12, "lat": 28.53, "datestr": "2014年06月18日"}, {"name": "武汉阅景汇投资发展有限公司", "lon": 114.03, "lat": 30.58, "datestr": "2014年06月19日"}, {"name": "江西嘉君置业有限公司", "lon": 114.93, "lat": 25.87, "datestr": "2014年07月04日"}, {"name": "高屋置业", "lon": 106.57, "lat": 29.6, "datestr": "2014年7月4日"}, {"name": "同创金泰项目管理(北京)有限公司", "lon": 116.43, "lat": 39.92, "datestr": "2014年07月11日"}, {"name": "安徽明天置业投资集团有限公司", "lon": 117.3, "lat": 31.87, "datestr": "2014年08月28日"}, {"name": "国美控股集团广州有限公司", "lon": 113.35, "lat": 23.12, "datestr": "2014年08月29日"}, {"name": "传奇文化发展有限公司", "lon": 116.43, "lat": 39.92, "datestr": "2014年10月20日"}, {"name": "香海生物科技", "lon": 113.35, "lat": 23.12, "datestr": "2014年10月22日"}, {"name": "山东贝嘉豪置业有限公司", "lon": 117.07, "lat": 36.68, "datestr": "2014年10月31日"}, {"name": "金科产业", "lon": 116.43, "lat": 39.92, "datestr": "2014年11月03日"}, {"name": "河南山顶金冠置业有限公司", "lon": 113.65, "lat": 34.78, "datestr": "2014年11月12日"}, {"name": "金马源投资", "lon": 102.72, "lat": 25.03, "datestr": "2014年11月27日"}, {"name": "中核泽农投资有限公司", "lon": 116.65, "lat": 39.92, "datestr": "2015年02月11日"}, {"name": "北京东方艺彩装饰工程有限公司", "lon": 116.28, "lat": 39.85, "datestr": "2015年03月11日"}, {"name": "启皓", "lon": 116.43, "lat": 39.92, "datestr": "2015年03月19日"}, {"name": "南京运昌置业发展有限公司(分支机构)", "lon": 118.75, "lat": 32.03, "datestr": "2015年04月17日"}, {"name": "南京中建东孚置业有限公司", "lon": 118.62, "lat": 32.05, "datestr": "2015年05月14日"}, {"name": "北京美得你装饰设计有限公司", "lon": 116.28, "lat": 39.85, "datestr": "2015年05月15日"}, {"name": "丝绸之路联合投资有限公司", "lon": 116.42, "lat": 39.93, "datestr": "2015年06月03日"}, {"name": "广州市楹浦实业有限公司", "lon": 113.27, "lat": 23.17, "datestr": "2015年06月04日"}, {"name": "桐木控股", "lon": 112.93, "lat": 28.23, "datestr": "2015年06月10日"}, {"name": "广东靓房通信息科技有限公司", "lon": 113.3, "lat": 22.8, "datestr": "2015年06月18日"}, {"name": "苏州渝瑞房地产开发有限公司", "lon": 120.63, "lat": 31.37, "datestr": "2015年06月19日"}, {"name": "佛山置华置业有限公司", "lon": 113.23, "lat": 23.13, "datestr": "2015年07月09日"}, {"name": "天茂置业(南京)有限公司", "lon": 118.75, "lat": 32.03, "datestr": "2015年07月29日"}, {"name": "潞盈科贸", "lon": 113.22, "lat": 36.33, "datestr": "2015年08月24日"}, {"name": "深圳市金地投资管理有限公司(分支机构)", "lon": 113.92, "lat": 22.52, "datestr": "2015年09月14日"}, {"name": "沃逸新能源科技(江苏)有限公司", "lon": 120.98, "lat": 31.38, "datestr": "2015年10月09日"}, {"name": "深圳市瀚邦科技有限公司", "lon": 114.05, "lat": 22.53, "datestr": "2015年10月23日"}, {"name": "深圳怀德房地产开发", "lon": 113.9, "lat": 22.57, "datestr": "2015年10月28日"}, {"name": "银狮", "lon": 103.52, "lat": 30.58, "datestr": "2015年11月06日"}, {"name": "新昌控股", "lon": 116.43, "lat": 39.92, "datestr": "2015年11月20日"}, {"name": "保利江苏", "lon": 118.8, "lat": 32.05, "datestr": "2015年12月18日"}, {"name": "荣欣装潢设计", "lon": 121.4, "lat": 31.25, "datestr": "2016年01月07日"}, {"name": "华彩金建材", "lon": 104.05, "lat": 30.65, "datestr": "2016年01月13日"}, {"name": "颂天元", "lon": 119.92, "lat": 28.45, "datestr": "2016年02月15日"}, {"name": "志特", "lon": 116.32, "lat": 26.83, "datestr": "2016年03月25日"}, {"name": "东方瑞迪投资", "lon": 110.3, "lat": 20.03, "datestr": "2016年03月25日"}, {"name": "海南融创基业房地产有限公司", "lon": 110.3, "lat": 20.03, "datestr": "2016年08月08日"}, {"name": "中建恒基", "lon": 116.28, "lat": 39.85, "datestr": "2017年04月21日"}, {"name": "中蓝投资", "lon": 120.38, "lat": 36.07, "datestr": "2017年07月11日"}]